core/greenlang/__init__.py
core/greenlang/_version.py
core/greenlang/agents/mock.py
core/greenlang/cards/__init__.py
core/greenlang/cards/generator.py
core/greenlang/cards/templates.py
core/greenlang/cards/validator.py
core/greenlang/cli/__init__.py
core/greenlang/cli/__main__.py
core/greenlang/cli/cmd_doctor.py
core/greenlang/cli/cmd_init.py
core/greenlang/cli/cmd_pack.py
core/greenlang/cli/cmd_policy.py
core/greenlang/cli/cmd_run.py
core/greenlang/cli/cmd_verify.py
core/greenlang/cli/main.py
core/greenlang/hub/__init__.py
core/greenlang/hub/index.py
core/greenlang/packs/installer.py
core/greenlang/packs/loader.py
core/greenlang/packs/loader_simple.py
core/greenlang/packs/manifest.py
core/greenlang/packs/registry.py
core/greenlang/policy/enforcer.py
core/greenlang/policy/opa.py
core/greenlang/policy/bundles/install.rego
core/greenlang/policy/bundles/run.rego
core/greenlang/provenance/key_provider.py
core/greenlang/provenance/ledger.py
core/greenlang/provenance/sbom.py
core/greenlang/provenance/sign.py
core/greenlang/provenance/signing.py
core/greenlang/provenance/utils.py
core/greenlang/runtime/__init__.py
core/greenlang/runtime/executor.py
core/greenlang/runtime/golden.py
core/greenlang/sdk/__init__.py
core/greenlang/sdk/base.py
core/greenlang/sdk/context.py
core/greenlang/sdk/pipeline.py
core/greenlang/security/__init__.py
core/greenlang/security/network.py
core/greenlang/security/paths.py
core/greenlang/security/signatures.py
core/greenlang/utils/net.py
greenlang/__init__.py
greenlang/_version.py
greenlang/types.py
greenlang/agents/__init__.py
greenlang/agents/base.py
greenlang/agents/benchmark_agent.py
greenlang/agents/boiler_agent.py
greenlang/agents/building_profile_agent.py
greenlang/agents/carbon_agent.py
greenlang/agents/demo_agent.py
greenlang/agents/energy_balance_agent.py
greenlang/agents/field_layout_agent.py
greenlang/agents/fuel_agent.py
greenlang/agents/grid_factor_agent.py
greenlang/agents/intensity_agent.py
greenlang/agents/load_profile_agent.py
greenlang_cli-0.3.0.dist-info/licenses/LICENSE
greenlang_cli-0.3.0.dist-info/METADATA
greenlang_cli-0.3.0.dist-info/WHEEL
greenlang_cli-0.3.0.dist-info/entry_points.txt
greenlang_cli-0.3.0.dist-info/top_level.txt
greenlang_cli-0.3.0.dist-info/RECORD
