Metadata-Version: 2.4
Name: greenlang-cli
Version: 0.3.0
Summary: Climate Intelligence Platform - Enterprise infrastructure with powerful SDK for climate-aware applications
Home-page: https://greenlang.io
Author: GreenLang Maintainers
Author-email: GreenLang Maintainers <maintainers@greenlang.io>
License: MIT
Project-URL: Homepage, https://greenlang.io
Project-URL: Documentation, https://greenlang.io/docs
Project-URL: Repository, https://github.com/greenlang/greenlang
Project-URL: Bug Tracker, https://github.com/greenlang/greenlang/issues
Project-URL: Changelog, https://github.com/greenlang/greenlang/blob/main/CHANGELOG.md
Project-URL: Discord, https://discord.gg/greenlang
Keywords: climate,emissions,sustainability,carbon,green,environment,AI,orchestration,platform,infrastructure,framework,SDK,climate-intelligence,decarbonization,net-zero,ESG,HVAC,buildings,energy
Classifier: Development Status :: 4 - Beta
Classifier: Intended Audience :: Developers
Classifier: Intended Audience :: Science/Research
Classifier: Topic :: Scientific/Engineering :: Atmospheric Science
Classifier: Topic :: Software Development :: Libraries :: Application Frameworks
Classifier: License :: OSI Approved :: MIT License
Classifier: Programming Language :: Python :: 3
Classifier: Programming Language :: Python :: 3 :: Only
Classifier: Programming Language :: Python :: 3.10
Classifier: Programming Language :: Python :: 3.11
Classifier: Programming Language :: Python :: 3.12
Classifier: Operating System :: OS Independent
Classifier: Environment :: Console
Classifier: Framework :: Pydantic
Classifier: Natural Language :: English
Requires-Python: >=3.10
License-File: LICENSE
Requires-Dist: typer>=0.12
Requires-Dist: pydantic>=2.7
Requires-Dist: pyyaml>=6.0
Requires-Dist: rich>=13.0
Requires-Dist: jsonschema>=4.19.0
Requires-Dist: packaging>=22.0
Requires-Dist: python-dotenv>=1.0.0
Requires-Dist: typing-extensions>=4.9.0
Requires-Dist: httpx>=0.24.0
Requires-Dist: requests>=2.31.0
Requires-Dist: networkx>=3.0
Requires-Dist: tenacity>=8.2.3
Requires-Dist: psutil>=5.9.0
Provides-Extra: analytics
Requires-Dist: pandas>=2.0.0; extra == "analytics"
Requires-Dist: numpy>=1.24.0; extra == "analytics"
Provides-Extra: cli
Requires-Dist: click>=8.0.0; extra == "cli"
Requires-Dist: rich>=13.0.0; extra == "cli"
Provides-Extra: data
Requires-Dist: pandas>=2.0.0; extra == "data"
Requires-Dist: numpy>=1.24.0; extra == "data"
Requires-Dist: openpyxl>=3.1.0; extra == "data"
Requires-Dist: jinja2>=3.1.0; extra == "data"
Requires-Dist: weasyprint>=60.0; extra == "data"
Requires-Dist: sqlalchemy>=2.0.0; extra == "data"
Requires-Dist: alembic>=1.12.0; extra == "data"
Requires-Dist: psycopg2-binary>=2.9.0; extra == "data"
Requires-Dist: pymongo>=4.5.0; extra == "data"
Provides-Extra: llm
Requires-Dist: openai>=1.0.0; extra == "llm"
Requires-Dist: langchain>=0.1.0; extra == "llm"
Requires-Dist: langchain-openai>=0.0.5; extra == "llm"
Requires-Dist: langchain-community>=0.0.10; extra == "llm"
Requires-Dist: anthropic>=0.7.0; extra == "llm"
Requires-Dist: faiss-cpu>=1.7.4; extra == "llm"
Requires-Dist: sentence-transformers>=2.2.0; extra == "llm"
Requires-Dist: pypdf>=3.17.0; extra == "llm"
Requires-Dist: chromadb>=0.4.0; extra == "llm"
Provides-Extra: server
Requires-Dist: aiohttp>=3.8.0; extra == "server"
Requires-Dist: fastapi>=0.104.0; extra == "server"
Requires-Dist: uvicorn>=0.24.0; extra == "server"
Requires-Dist: redis>=5.0.0; extra == "server"
Requires-Dist: celery>=5.3.0; extra == "server"
Requires-Dist: prometheus-client>=0.18.0; extra == "server"
Requires-Dist: opentelemetry-api>=1.20.0; extra == "server"
Requires-Dist: structlog>=23.0.0; extra == "server"
Requires-Dist: gunicorn>=21.0.0; extra == "server"
Provides-Extra: security
Requires-Dist: cryptography>=41.0.0; extra == "security"
Requires-Dist: PyJWT>=2.8.0; extra == "security"
Provides-Extra: test
Requires-Dist: pytest>=7.4.0; extra == "test"
Requires-Dist: pytest-cov>=4.1.0; extra == "test"
Requires-Dist: pytest-asyncio>=0.21.0; extra == "test"
Requires-Dist: pytest-mock>=3.11.0; extra == "test"
Requires-Dist: pytest-timeout>=2.1.0; extra == "test"
Requires-Dist: pytest-xdist>=3.3.0; extra == "test"
Requires-Dist: pytest-benchmark>=4.0.0; extra == "test"
Requires-Dist: pytest-regressions>=2.5.0; extra == "test"
Requires-Dist: hypothesis>=6.80.0; extra == "test"
Requires-Dist: psutil>=5.9.0; extra == "test"
Requires-Dist: coverage[toml]>=7.2.0; extra == "test"
Requires-Dist: faker>=19.0.0; extra == "test"
Requires-Dist: responses>=0.23.0; extra == "test"
Requires-Dist: freezegun>=1.2.0; extra == "test"
Requires-Dist: factory-boy>=3.3.0; extra == "test"
Requires-Dist: greenlang[cli]; extra == "test"
Requires-Dist: greenlang[data]; extra == "test"
Requires-Dist: greenlang[analytics]; extra == "test"
Requires-Dist: greenlang[security]; extra == "test"
Provides-Extra: dev
Requires-Dist: mypy>=1.7.0; extra == "dev"
Requires-Dist: ruff>=0.1.0; extra == "dev"
Requires-Dist: black>=23.7.0; extra == "dev"
Requires-Dist: isort>=5.12.0; extra == "dev"
Requires-Dist: bandit>=1.7.0; extra == "dev"
Requires-Dist: types-PyYAML>=6.0.12; extra == "dev"
Requires-Dist: types-requests>=2.31.0; extra == "dev"
Requires-Dist: types-redis>=4.6.0; extra == "dev"
Requires-Dist: types-jsonschema>=4.19.0; extra == "dev"
Requires-Dist: ipython>=8.0.0; extra == "dev"
Requires-Dist: jupyter>=1.0.0; extra == "dev"
Requires-Dist: pre-commit>=3.0.0; extra == "dev"
Requires-Dist: watchdog>=3.0.0; extra == "dev"
Requires-Dist: docker>=6.1.0; extra == "dev"
Requires-Dist: kubernetes>=28.0.0; extra == "dev"
Requires-Dist: flake8>=6.0; extra == "dev"
Provides-Extra: doc
Requires-Dist: mkdocs>=1.5.0; extra == "doc"
Requires-Dist: mkdocs-material>=9.0.0; extra == "doc"
Requires-Dist: mkdocstrings>=0.23.0; extra == "doc"
Provides-Extra: full
Requires-Dist: greenlang[cli]; extra == "full"
Requires-Dist: greenlang[data]; extra == "full"
Requires-Dist: greenlang[analytics]; extra == "full"
Requires-Dist: greenlang[llm]; extra == "full"
Requires-Dist: greenlang[server]; extra == "full"
Requires-Dist: greenlang[security]; extra == "full"
Provides-Extra: all
Requires-Dist: greenlang[full]; extra == "all"
Requires-Dist: greenlang[test]; extra == "all"
Requires-Dist: greenlang[dev]; extra == "all"
Requires-Dist: greenlang[doc]; extra == "all"
Dynamic: author
Dynamic: home-page
Dynamic: license-file
Dynamic: requires-python
